CB2325NumericaG6/__init__.py
CB2325NumericaG6/aproximacao.py
CB2325NumericaG6/core.py
CB2325NumericaG6/erros.py
CB2325NumericaG6/integracao.py
CB2325NumericaG6/interpolacao.py
CB2325NumericaG6/polinomios.py
CB2325NumericaG6/raizes.py
CB2325NumericaG6/test_aproximacao.py
CB2325NumericaG6/test_integracao.py
CB2325NumericaG6/test_interpolacao.py
CB2325NumericaG6/test_polinomios.py
CB2325NumericaG6/test_raizes.py
CB2325NumericaG6/teste
CB2325NumericaG6/teste_erros.py
cb2325numericag6-1.2.1.dist-info/METADATA
cb2325numericag6-1.2.1.dist-info/WHEEL
cb2325numericag6-1.2.1.dist-info/entry_points.txt
cb2325numericag6-1.2.1.dist-info/licenses/LICENSE
cb2325numericag6-1.2.1.dist-info/RECORD
