Metadata-Version: 2.1
Name: CB2325NumericaG6
Version: 1.2.1
Summary: Alpha version of NumericaG6
Author-Email: Mateus Almeida Oliveira <al.mateus.oliveira@impatech.edu.br>
License: MIT
Classifier: Programming Language :: Python :: 3
Classifier: Operating System :: OS Independent
Requires-Python: >=3.9
Requires-Dist: matplotlib
Requires-Dist: numpy
